sigma/backends/sqlite/__init__.py
sigma/backends/sqlite/sqlite.py
pysigma_backend_sqlite-1.1.3.dist-info/METADATA
pysigma_backend_sqlite-1.1.3.dist-info/WHEEL
pysigma_backend_sqlite-1.1.3.dist-info/licenses/LICENSE
pysigma_backend_sqlite-1.1.3.dist-info/RECORD
