Metadata-Version: 2.4
Name: pySigma-backend-sqlite
Version: 1.1.3
Summary: pySigma sqlite backend
License-Expression: LGPL-3.0-only
License-File: LICENSE
Author: wagga
Requires-Python: >=3.10,<4.0
Classifier: Programming Language :: Python :: 3
Classifier: Programming Language :: Python :: 3.10
Classifier: Programming Language :: Python :: 3.11
Classifier: Programming Language :: Python :: 3.12
Classifier: Programming Language :: Python :: 3.13
Classifier: Programming Language :: Python :: 3.14
Requires-Dist: pysigma (>=1.0.2,<=2.0)
Project-URL: Repository, https://github.com/SigmaHQ/pySigma-backend-sqlite
